{
  "article_id": "pg-083",
  "score": 93,
  "category_scores": {
    "content_quality": 29,
    "seo": 24,
    "eeat": 14,
    "technical": 13,
    "ai_citation_readiness": 13
  },
  "hard_gate_results": {
    "persona_consistency": true,
    "fact_traceability": true,
    "research_gate": true,
    "content_uniqueness": true,
    "article_contract_uniqueness": true,
    "title_template_uniqueness": true,
    "subtitle_keyword_coverage": true,
    "structure_variation": true,
    "content_template_variation": true,
    "visual_elements": true,
    "patent_case_examples": true,
    "heading_quality": true,
    "body_length": true,
    "internal_links": true,
    "no_ad_slots": true
  },
  "compared_rows": [],
  "similarity_signals": {
    "title_pattern_signature": "bms-pack-comparison-진단·충전·열관리",
    "subtitle_pattern_signature": "comparison-권리 신호 비교",
    "opening_frame": "BMS 기능 분해표는 숫자를 보기 좋게 놓는 표가 아니라 서로 다른 근거",
    "section_role_sequence": "BMS 기능 분해표에서 섞지 말아야 할 값 > 진단·충전·열관리과 BMS와 팩 비교 축 > BMS 기능 분해표에서 '권리 신호 비교' 우선 검토와 보류 기준 > '알고리즘과 센서' 비교표 반영 방법 > BMS 알고리즘 문헌을 센서·진단·충전 제어로 나누는 상황에서 출처별 차이를 공식 원문으로 맞추는 법 > 하드웨어 구성과 소프트웨어 로직을 분리하는 순간 뒤에 남길 질문",
    "visual_sequence": "comparison-table,decision-box,risk-labels",
    "cta_type": "related-guide-and-cluster-link"
  },
  "repair_attempted": true,
  "remaining_risks": "공식 사이트 화면명과 제도 문구는 개편될 수 있으므로 독자에게 원문 확인을 안내했다."
}